{
  "schemaVersion": "1.0",
  "type": "build_hook_delta",
  "date": "2026-06-22",
  "title": "THETA Control Room — Build Hook Delta",
  "mode": "Automated build-script update.",
  "allowNewProjects": false,
  "changedProjects": [
    {
      "id": "creosote",
      "changeType": "Build hook update",
      "status": "active",
      "latestVersion": "v19.2.6",
      "shipReadiness": 10,
      "sourceCertainty": "high",
      "formatsNow": [
        "VST3",
        "AU"
      ],
      "artifact": "/Users/steveneal/Library/Audio/Plug-Ins/VST3/CREOSOTE.vst3",
      "lastKnownStatus": "Build hook reported latest project state.",
      "blocker": "Needs test result.",
      "nextAction": "Fixed COMPRESS G/R meter freeze on transport stop (meter-clock freshness gate). Verify; consider same for METERING L/R/GR. Awaiting new presets.",
      "tomorrowFirstAction": "Fixed COMPRESS G/R meter freeze on transport stop (meter-clock freshness gate). Verify; consider same for METERING L/R/GR. Awaiting new presets.",
      "endStatus": "Build hook reported CREOSOTE v19.2.6."
    }
  ],
  "dashboardUpdateDecision": {
    "dashboardDataChanged": true,
    "tomorrowFirstControlRoomAction": "Review build-hook update for CREOSOTE."
  }
}
